uniq_char.py
uniq_char-0.1.0.dist-info/WHEEL
uniq_char-0.1.0.dist-info/METADATA
uniq_char-0.1.0.dist-info/RECORD
