Metadata-Version: 2.1
Name: uniq-char
Version: 0.1.0
Summary: program to find q-ty of unique chars in string
Author: Volodymyr Siabro
Author-email: siabrovova@gmail.com
Requires-Python: >=3.9,<4.0
Classifier: Programming Language :: Python :: 3
Classifier: Programming Language :: Python :: 3.10
Classifier: Programming Language :: Python :: 3.9
